CHANGELOG.md
LICENSE
README.md
script_master_helper/__init__.py
script_master_helper/executor/__init__.py
script_master_helper/executor/client/__init__.py
script_master_helper/executor/client/api.py
script_master_helper/executor/client/client.py
script_master_helper/executor/client/errors.py
script_master_helper/executor/schemas.py
script_master_helper/utils.py
script_master_helper/workplanner/__init__.py
script_master_helper/workplanner/client/__init__.py
script_master_helper/workplanner/client/api.py
script_master_helper/workplanner/client/client.py
script_master_helper/workplanner/client/errors.py
script_master_helper/workplanner/enums.py
script_master_helper/workplanner/schemas.py
script_master_helper-0.0.2.dist-info/LICENSE
script_master_helper-0.0.2.dist-info/WHEEL
script_master_helper-0.0.2.dist-info/METADATA
script_master_helper-0.0.2.dist-info/RECORD
