Metadata-Version: 2.1
Name: script-master-helper
Version: 0.0.2
Summary: 
Home-page: https://github.com/pavelmaksimov/script-master-helper
License: Apache-2.0
Author: Pavel Maksimov
Author-email: vur21@ya.ru
Requires-Python: >=3.10,<4.0
Classifier: License :: OSI Approved :: Apache Software License
Classifier: Programming Language :: Python :: 3
Classifier: Programming Language :: Python :: 3.10
Classifier: Programming Language :: Python :: 3.11
Requires-Dist: aiohttp
Requires-Dist: asyncio
Requires-Dist: pendulum (>=2.1.2,<3.0.0)
